collective.volto.slotseditor-1.1a1-py3.12-nspkg.pth
collective/volto/slotseditor/__init__.py
collective/volto/slotseditor/configure.zcml
collective/volto/slotseditor/interfaces.py
collective/volto/slotseditor/permissions.zcml
collective/volto/slotseditor/setuphandlers.py
collective/volto/slotseditor/testing.py
collective/volto/slotseditor/api/__init__.py
collective/volto/slotseditor/api/configure.zcml
collective/volto/slotseditor/api/deserializer.py
collective/volto/slotseditor/api/serializers/__init__.py
collective/volto/slotseditor/api/serializers/configure.zcml
collective/volto/slotseditor/api/serializers/slotseditor_settings.py
collective/volto/slotseditor/api/services/__init__.py
collective/volto/slotseditor/api/services/configure.zcml
collective/volto/slotseditor/api/services/settings/__init__.py
collective/volto/slotseditor/api/services/settings/configure.zcml
collective/volto/slotseditor/api/services/settings/get.py
collective/volto/slotseditor/browser/__init__.py
collective/volto/slotseditor/browser/configure.zcml
collective/volto/slotseditor/browser/overrides/.gitkeep
collective/volto/slotseditor/browser/static/.gitkeep
collective/volto/slotseditor/controlpanels/__init__.py
collective/volto/slotseditor/controlpanels/configure.zcml
collective/volto/slotseditor/controlpanels/slotseditor/__init__.py
collective/volto/slotseditor/controlpanels/slotseditor/configure.zcml
collective/volto/slotseditor/controlpanels/slotseditor/controlpanel.py
collective/volto/slotseditor/locales/README.rst
collective/volto/slotseditor/locales/__init__.py
collective/volto/slotseditor/locales/pretagov.website.pot
collective/volto/slotseditor/locales/update.py
collective/volto/slotseditor/locales/update.sh
collective/volto/slotseditor/locales/en/LC_MESSAGES/pretagov.website.po
collective/volto/slotseditor/profiles/default/browserlayer.xml
collective/volto/slotseditor/profiles/default/catalog.xml
collective/volto/slotseditor/profiles/default/controlpanel.xml
collective.volto.slotseditor-1.1a1.dist-info/LICENSE.GPL
collective.volto.slotseditor-1.1a1.dist-info/LICENSE.rst
collective.volto.slotseditor-1.1a1.dist-info/METADATA
collective.volto.slotseditor-1.1a1.dist-info/WHEEL
collective.volto.slotseditor-1.1a1.dist-info/entry_points.txt
collective.volto.slotseditor-1.1a1.dist-info/namespace_packages.txt
collective.volto.slotseditor-1.1a1.dist-info/top_level.txt
collective.volto.slotseditor-1.1a1.dist-info/RECORD
