Metadata-Version: 2.1
Name: collective.volto.slotseditor
Version: 1.1a1
Summary: An add-on for Plone
Home-page: https://github.com/collective/collective.volto.slotseditor
Author: PretaGov
Author-email: jeff.bledsoe@pretagov.com.au
License: GPL version 2
Project-URL: PyPI, https://pypi.org/project/collective.volto.slotseditor/
Project-URL: Source, https://github.com/collective/collective.volto.slotseditor
Project-URL: Tracker, https://github.com/collective/collective.volto.slotseditor/issues
Keywords: Python Plone CMS
Classifier: Development Status :: 4 - Beta
Classifier: Environment :: Web Environment
Classifier: Framework :: Plone
Classifier: Framework :: Plone :: Addon
Classifier: Framework :: Plone :: 5.2
Classifier: Framework :: Plone :: 6.0
Classifier: Programming Language :: Python
Classifier: Programming Language :: Python :: 3.7
Classifier: Programming Language :: Python :: 3.8
Classifier: Programming Language :: Python :: 3.9
Classifier: Operating System :: OS Independent
Classifier: License :: OSI Approved :: GNU General Public License v2 (GPLv2)
Requires-Python: >=3.7
License-File: LICENSE.GPL
License-File: LICENSE.rst
Requires-Dist: setuptools
Requires-Dist: z3c.jbot
Requires-Dist: plone.api >=1.8.4
Requires-Dist: plone.app.dexterity
Provides-Extra: test
Requires-Dist: plone.app.testing ; extra == 'test'
Requires-Dist: plone.testing >=5.0.0 ; extra == 'test'
Requires-Dist: plone.app.contenttypes ; extra == 'test'
Requires-Dist: plone.app.robotframework[debug] ; extra == 'test'
